license
pyvplm/__init__.py
pyvplm/addon/__init__.py
pyvplm/addon/comsoladdon.py
pyvplm/addon/pixdoe.py
pyvplm/addon/variablepowerlaw.py
pyvplm/addon/variablepowerlaw.py.bak
pyvplm/core/__init__.py
pyvplm/core/definition.py
pyvplm/core/definition.py.bak
pyvplm-0.1.0.dist-info/license
pyvplm-0.1.0.dist-info/WHEEL
pyvplm-0.1.0.dist-info/METADATA
pyvplm-0.1.0.dist-info/RECORD
