Metadata-Version: 2.1
Name: pyvplm
Version: 0.1.0
Summary: Variable Power-Law regression Models tool
Home-page: https://github.com/SizingLab/pyvplm
License: MIT
Keywords: regression,dimensional analysis,metamodeling
Author: Aurélien REYSSET
Author-email: aurelien.reysset@insa-toulouse.fr
Requires-Python: >=3.6.1,<4.0.0
Classifier: Environment :: Console
Classifier: Intended Audience :: Education
Classifier: Intended Audience :: Science/Research
Classifier: License :: OSI Approved :: MIT License
Classifier: Natural Language :: English
Classifier: Operating System :: OS Independent
Classifier: Programming Language :: Python :: 3
Classifier: Programming Language :: Python :: 3.7
Classifier: Programming Language :: Python :: 3.8
Classifier: Topic :: Scientific/Engineering :: Physics
Requires-Dist: ipython
Requires-Dist: ipywidgets
Requires-Dist: matplotlib
Requires-Dist: numpy
Requires-Dist: pandas
Requires-Dist: pint
Requires-Dist: pydoe2
Requires-Dist: scikit-learn
Requires-Dist: scipy
Requires-Dist: sympy
Requires-Dist: xlrd
Requires-Dist: xlwt
